lairningdecisions/__init__.py
lairningdecisions/backoffice/__init__.py
lairningdecisions/backoffice/api.py
lairningdecisions/server/__init__.py
lairningdecisions/server/api.py
lairningdecisions/trainer/__init__.py
lairningdecisions/trainer/api.py
lairningdecisions/utils/__init__.py
lairningdecisions/utils/db.py
lairningdecisions/utils/recreate_backoffice_db.py
lairningdecisions/utils/recreate_trainer_db.py
lairningdecisions/utils/scaler_config.py
lairningdecisions/utils/utils.py
lairning_decisions-0.1.3.dist-info/LICENSE
lairning_decisions-0.1.3.dist-info/METADATA
lairning_decisions-0.1.3.dist-info/WHEEL
lairning_decisions-0.1.3.dist-info/top_level.txt
lairning_decisions-0.1.3.dist-info/RECORD
