Metadata-Version: 2.1
Name: lairning-decisions
Version: 0.1.3
Summary: lairning Decisions
Home-page: https://github.com/lairning/drlpackage
Author: md_lairning
Author-email: md.lairning@gmail.com
License: MIT License
Platform: UNKNOWN
Classifier: Programming Language :: Python :: 3.7
Classifier: License :: OSI Approved :: GNU Lesser General Public License v3 or later (LGPLv3+)
Classifier: Operating System :: POSIX :: Linux
Classifier: Topic :: Scientific/Engineering :: Artificial Intelligence
Classifier: Development Status :: 4 - Beta
Requires-Python: >=3.7
License-File: LICENSE
